jiku_data-0.1.10.dist-info/licenses/LICENSE
jikudata/__init__.py
jikudata/io.py
jikudata/_cls/__init__.py
jikudata/_cls/dataset.py
jikudata/_cls/params.py
jikudata/_cls/results.py
jikudata/datasets/__init__.py
jikudata/datasets/AnimalDepression/__init__.py
jikudata/datasets/AnimalDepression/data.csv
jikudata/datasets/Antidepressant/__init__.py
jikudata/datasets/Antidepressant/data.csv
jikudata/datasets/Besier2009muscleforces/__init__.py
jikudata/datasets/Besier2009muscleforces/data.csv
jikudata/datasets/Besier2009muscleforces/expected_results.npz
jikudata/datasets/ConstructionUnequalSampleSizes/__init__.py
jikudata/datasets/ConstructionUnequalSampleSizes/data.csv
jikudata/datasets/DAgostino1990/__init__.py
jikudata/datasets/DAgostino1990/data.csv
jikudata/datasets/DaysInHospital/__init__.py
jikudata/datasets/DaysInHospital/data.csv
jikudata/datasets/Dorn2012/__init__.py
jikudata/datasets/Dorn2012/data.csv
jikudata/datasets/Dorn2012/expected_results.npz
jikudata/datasets/Dorn2012manova/__init__.py
jikudata/datasets/Dorn2012manova/data.csv
jikudata/datasets/Dorn2012manova/expected_results.npz
jikudata/datasets/FitnessClub/__init__.py
jikudata/datasets/FitnessClub/data.csv
jikudata/datasets/Groceries/__init__.py
jikudata/datasets/Groceries/data.csv
jikudata/datasets/HELPHomeless/__init__.py
jikudata/datasets/HELPHomeless/data.csv
jikudata/datasets/Neptune1999kneekin/__init__.py
jikudata/datasets/Neptune1999kneekin/data.csv
jikudata/datasets/Neptune1999kneekin/expected_results.npz
jikudata/datasets/Pataky2014cop/__init__.py
jikudata/datasets/Pataky2014cop/data.csv
jikudata/datasets/Pataky2014cop/expected_results.npz
jikudata/datasets/PlantarArchAngle/__init__.py
jikudata/datasets/PlantarArchAngle/data.csv
jikudata/datasets/PlantarArchAngle/expected_results.npz
jikudata/datasets/QIMacros/__init__.py
jikudata/datasets/QIMacros/data.csv
jikudata/datasets/RSFlavor/__init__.py
jikudata/datasets/RSFlavor/data.csv
jikudata/datasets/RSItalian/__init__.py
jikudata/datasets/RSItalian/data.csv
jiku_data-0.1.10.dist-info/METADATA
jiku_data-0.1.10.dist-info/WHEEL
jiku_data-0.1.10.dist-info/top_level.txt
jiku_data-0.1.10.dist-info/RECORD
