Metadata-Version: 2.4
Name: jiku-data
Version: 0.1.10
Summary: 'Open source datasets, component of Jiku Core
Author-email: Jiku Pro <admin@jiku.pro>
Project-URL: Homepage, https://github.com/jiku-pro/jiku-data
Project-URL: Source, https://github.com/jiku-pro/jiku-data
Project-URL: Bug Reports, https://github.com/jiku-pro/jiku-data/issues
Keywords: datasets,data analysis,functional data analysis,time series analysis
Classifier: Development Status :: 4 - Beta
Classifier: License :: OSI Approved :: GNU General Public License v3 (GPLv3)
Classifier: Topic :: Scientific/Engineering
Classifier: Programming Language :: Python :: 3.9
Requires-Python: >=3.9
License-File: LICENSE
Requires-Dist: numpy
Requires-Dist: tables
Dynamic: license-file
